{
  "id": "00000000-0000-0000-0000-000000000000",
  "prevId": "",
  "version": "7",
  "dialect": "postgresql",
  "tables": {
    "public.IntegrationInstanceState": {
      "name": "IntegrationInstanceState",
      "schema": "",
      "columns": {
        "pub_id": {
          "name": "pub_id",
          "type": "text",
          "primaryKey": false,
          "notNull": true
        },
        "instance_id": {
          "name": "instance_id",
          "type": "text",
          "primaryKey": false,
          "notNull": true
        },
        "state": {
          "name": "state",
          "type": "jsonb",
          "primaryKey": false,
          "notNull": true
        }
      },
      "indexes": {
        "IntegrationInstanceState_pub_id_instance_id_key": {
          "name": "IntegrationInstanceState_pub_id_instance_id_key",
          "columns": [
            {
              "expression": "pub_id",
              "asc": true,
              "nulls": "last",
              "opclass": "text_ops",
              "isExpression": false
            },
            {
              "expression": "instance_id",
              "asc": true,
              "nulls": "last",
              "opclass": "text_ops",
              "isExpression": false
            }
          ],
          "isUnique": true,
          "concurrently": false,
          "method": "btree",
          "with": {}
        }
      },
      "foreignKeys": {
        "IntegrationInstanceState_pub_id_fkey": {
          "name": "IntegrationInstanceState_pub_id_fkey",
          "tableFrom": "IntegrationInstanceState",
          "tableTo": "pubs",
          "schemaTo": "public",
          "columnsFrom": [
            "pub_id"
          ],
          "columnsTo": [
            "id"
          ],
          "onDelete": "restrict",
          "onUpdate": "cascade"
        },
        "IntegrationInstanceState_instance_id_fkey": {
          "name": "IntegrationInstanceState_instance_id_fkey",
          "tableFrom": "IntegrationInstanceState",
          "tableTo": "integration_instances",
          "schemaTo": "public",
          "columnsFrom": [
            "instance_id"
          ],
          "columnsTo": [
            "id"
          ],
          "onDelete": "restrict",
          "onUpdate": "cascade"
        }
      },
      "compositePrimaryKeys": {},
      "uniqueConstraints": {},
      "checkConstraints": {},
      "policies": {},
      "isRLSEnabled": false
    },
    "public.pub_types": {
      "name": "pub_types",
      "schema": "",
      "columns": {
        "id": {
          "name": "id",
          "type": "text",
          "primaryKey": true,
          "notNull": true,
          "default": "gen_random_uuid()"
        },
        "created_at": {
          "name": "created_at",
          "type": "timestamp(3)",
          "primaryKey": false,
          "notNull": true,
          "default": "CURRENT_TIMESTAMP"
        },
        "updated_at": {
          "name": "updated_at",
          "type": "timestamp(3)",
          "primaryKey": false,
          "notNull": true,
          "default": "CURRENT_TIMESTAMP"
        },
        "community_id": {
          "name": "community_id",
          "type": "text",
          "primaryKey": false,
          "notNull": true
        },
        "name": {
          "name": "name",
          "type": "text",
          "primaryKey": false,
          "notNull": true
        },
        "description": {
          "name": "description",
          "type": "text",
          "primaryKey": false,
          "notNull": false
        }
      },
      "indexes": {},
      "foreignKeys": {
        "pub_types_community_id_fkey": {
          "name": "pub_types_community_id_fkey",
          "tableFrom": "pub_types",
          "tableTo": "communities",
          "schemaTo": "public",
          "columnsFrom": [
            "community_id"
          ],
          "columnsTo": [
            "id"
          ],
          "onDelete": "restrict",
          "onUpdate": "cascade"
        }
      },
      "compositePrimaryKeys": {},
      "uniqueConstraints": {},
      "checkConstraints": {},
      "policies": {},
      "isRLSEnabled": false
    },
    "public.action_claim": {
      "name": "action_claim",
      "schema": "",
      "columns": {
        "id": {
          "name": "id",
          "type": "text",
          "primaryKey": true,
          "notNull": true,
          "default": "gen_random_uuid()"
        },
        "stage_id": {
          "name": "stage_id",
          "type": "text",
          "primaryKey": false,
          "notNull": true
        },
        "pub_id": {
          "name": "pub_id",
          "type": "text",
          "primaryKey": false,
          "notNull": true
        },
        "user_id": {
          "name": "user_id",
          "type": "text",
          "primaryKey": false,
          "notNull": true
        },
        "releasedAt": {
          "name": "releasedAt",
          "type": "timestamp(3)",
          "primaryKey": false,
          "notNull": false
        },
        "created_at": {
          "name": "created_at",
          "type": "timestamp(3)",
          "primaryKey": false,
          "notNull": true,
          "default": "CURRENT_TIMESTAMP"
        },
        "updated_at": {
          "name": "updated_at",
          "type": "timestamp(3)",
          "primaryKey": false,
          "notNull": true,
          "default": "CURRENT_TIMESTAMP"
        }
      },
      "indexes": {},
      "foreignKeys": {
        "action_claim_stage_id_fkey": {
          "name": "action_claim_stage_id_fkey",
          "tableFrom": "action_claim",
          "tableTo": "stages",
          "schemaTo": "public",
          "columnsFrom": [
            "stage_id"
          ],
          "columnsTo": [
            "id"
          ],
          "onDelete": "restrict",
          "onUpdate": "cascade"
        },
        "action_claim_pub_id_fkey": {
          "name": "action_claim_pub_id_fkey",
          "tableFrom": "action_claim",
          "tableTo": "pubs",
          "schemaTo": "public",
          "columnsFrom": [
            "pub_id"
          ],
          "columnsTo": [
            "id"
          ],
          "onDelete": "restrict",
          "onUpdate": "cascade"
        },
        "action_claim_user_id_fkey": {
          "name": "action_claim_user_id_fkey",
          "tableFrom": "action_claim",
          "tableTo": "users",
          "schemaTo": "public",
          "columnsFrom": [
            "user_id"
          ],
          "columnsTo": [
            "id"
          ],
          "onDelete": "restrict",
          "onUpdate": "cascade"
        }
      },
      "compositePrimaryKeys": {},
      "uniqueConstraints": {},
      "checkConstraints": {},
      "policies": {},
      "isRLSEnabled": false
    },
    "public.action_move": {
      "name": "action_move",
      "schema": "",
      "columns": {
        "id": {
          "name": "id",
          "type": "text",
          "primaryKey": true,
          "notNull": true,
          "default": "gen_random_uuid()"
        },
        "source_stage_id": {
          "name": "source_stage_id",
          "type": "text",
          "primaryKey": false,
          "notNull": true
        },
        "destination_stage_id": {
          "name": "destination_stage_id",
          "type": "text",
          "primaryKey": false,
          "notNull": true
        },
        "pub_id": {
          "name": "pub_id",
          "type": "text",
          "primaryKey": false,
          "notNull": true
        },
        "user_id": {
          "name": "user_id",
          "type": "text",
          "primaryKey": false,
          "notNull": true
        },
        "note": {
          "name": "note",
          "type": "text",
          "primaryKey": false,
          "notNull": true
        },
        "created_at": {
          "name": "created_at",
          "type": "timestamp(3)",
          "primaryKey": false,
          "notNull": true,
          "default": "CURRENT_TIMESTAMP"
        },
        "updated_at": {
          "name": "updated_at",
          "type": "timestamp(3)",
          "primaryKey": false,
          "notNull": true,
          "default": "CURRENT_TIMESTAMP"
        }
      },
      "indexes": {},
      "foreignKeys": {
        "action_move_source_stage_id_fkey": {
          "name": "action_move_source_stage_id_fkey",
          "tableFrom": "action_move",
          "tableTo": "stages",
          "schemaTo": "public",
          "columnsFrom": [
            "source_stage_id"
          ],
          "columnsTo": [
            "id"
          ],
          "onDelete": "restrict",
          "onUpdate": "cascade"
        },
        "action_move_destination_stage_id_fkey": {
          "name": "action_move_destination_stage_id_fkey",
          "tableFrom": "action_move",
          "tableTo": "stages",
          "schemaTo": "public",
          "columnsFrom": [
            "destination_stage_id"
          ],
          "columnsTo": [
            "id"
          ],
          "onDelete": "restrict",
          "onUpdate": "cascade"
        },
        "action_move_pub_id_fkey": {
          "name": "action_move_pub_id_fkey",
          "tableFrom": "action_move",
          "tableTo": "pubs",
          "schemaTo": "public",
          "columnsFrom": [
            "pub_id"
          ],
          "columnsTo": [
            "id"
          ],
          "onDelete": "restrict",
          "onUpdate": "cascade"
        },
        "action_move_user_id_fkey": {
          "name": "action_move_user_id_fkey",
          "tableFrom": "action_move",
          "tableTo": "users",
          "schemaTo": "public",
          "columnsFrom": [
            "user_id"
          ],
          "columnsTo": [
            "id"
          ],
          "onDelete": "restrict",
          "onUpdate": "cascade"
        }
      },
      "compositePrimaryKeys": {},
      "uniqueConstraints": {},
      "checkConstraints": {},
      "policies": {},
      "isRLSEnabled": false
    },
    "public.pub_values": {
      "name": "pub_values",
      "schema": "",
      "columns": {
        "id": {
          "name": "id",
          "type": "text",
          "primaryKey": true,
          "notNull": true,
          "default": "gen_random_uuid()"
        },
        "field_id": {
          "name": "field_id",
          "type": "text",
          "primaryKey": false,
          "notNull": true
        },
        "value": {
          "name": "value",
          "type": "jsonb",
          "primaryKey": false,
          "notNull": true
        },
        "pub_id": {
          "name": "pub_id",
          "type": "text",
          "primaryKey": false,
          "notNull": true
        },
        "created_at": {
          "name": "created_at",
          "type": "timestamp(3)",
          "primaryKey": false,
          "notNull": true,
          "default": "CURRENT_TIMESTAMP"
        },
        "updated_at": {
          "name": "updated_at",
          "type": "timestamp(3)",
          "primaryKey": false,
          "notNull": true,
          "default": "CURRENT_TIMESTAMP"
        }
      },
      "indexes": {},
      "foreignKeys": {
        "pub_values_pub_id_fkey": {
          "name": "pub_values_pub_id_fkey",
          "tableFrom": "pub_values",
          "tableTo": "pubs",
          "schemaTo": "public",
          "columnsFrom": [
            "pub_id"
          ],
          "columnsTo": [
            "id"
          ],
          "onDelete": "cascade",
          "onUpdate": "cascade"
        },
        "pub_values_field_id_fkey": {
          "name": "pub_values_field_id_fkey",
          "tableFrom": "pub_values",
          "tableTo": "pub_fields",
          "schemaTo": "public",
          "columnsFrom": [
            "field_id"
          ],
          "columnsTo": [
            "id"
          ],
          "onDelete": "restrict",
          "onUpdate": "cascade"
        }
      },
      "compositePrimaryKeys": {},
      "uniqueConstraints": {},
      "checkConstraints": {},
      "policies": {},
      "isRLSEnabled": false
    },
    "public._PubFieldToPubType": {
      "name": "_PubFieldToPubType",
      "schema": "",
      "columns": {
        "A": {
          "name": "A",
          "type": "text",
          "primaryKey": false,
          "notNull": true
        },
        "B": {
          "name": "B",
          "type": "text",
          "primaryKey": false,
          "notNull": true
        }
      },
      "indexes": {
        "_PubFieldToPubType_AB_unique": {
          "name": "_PubFieldToPubType_AB_unique",
          "columns": [
            {
              "expression": "A",
              "asc": true,
              "nulls": "last",
              "opclass": "text_ops",
              "isExpression": false
            },
            {
              "expression": "B",
              "asc": true,
              "nulls": "last",
              "opclass": "text_ops",
              "isExpression": false
            }
          ],
          "isUnique": true,
          "concurrently": false,
          "method": "btree",
          "with": {}
        },
        "_PubFieldToPubType_B_index": {
          "name": "_PubFieldToPubType_B_index",
          "columns": [
            {
              "expression": "B",
              "asc": true,
              "nulls": "last",
              "opclass": "text_ops",
              "isExpression": false
            }
          ],
          "isUnique": false,
          "concurrently": false,
          "method": "btree",
          "with": {}
        }
      },
      "foreignKeys": {
        "_PubFieldToPubType_A_fkey": {
          "name": "_PubFieldToPubType_A_fkey",
          "tableFrom": "_PubFieldToPubType",
          "tableTo": "pub_fields",
          "schemaTo": "public",
          "columnsFrom": [
            "A"
          ],
          "columnsTo": [
            "id"
          ],
          "onDelete": "cascade",
          "onUpdate": "cascade"
        },
        "_PubFieldToPubType_B_fkey": {
          "name": "_PubFieldToPubType_B_fkey",
          "tableFrom": "_PubFieldToPubType",
          "tableTo": "pub_types",
          "schemaTo": "public",
          "columnsFrom": [
            "B"
          ],
          "columnsTo": [
            "id"
          ],
          "onDelete": "cascade",
          "onUpdate": "cascade"
        }
      },
      "compositePrimaryKeys": {},
      "uniqueConstraints": {},
      "checkConstraints": {},
      "policies": {},
      "isRLSEnabled": false
    },
    "public.pub_fields": {
      "name": "pub_fields",
      "schema": "",
      "columns": {
        "id": {
          "name": "id",
          "type": "text",
          "primaryKey": true,
          "notNull": true,
          "default": "gen_random_uuid()"
        },
        "name": {
          "name": "name",
          "type": "text",
          "primaryKey": false,
          "notNull": true
        },
        "created_at": {
          "name": "created_at",
          "type": "timestamp(3)",
          "primaryKey": false,
          "notNull": true,
          "default": "CURRENT_TIMESTAMP"
        },
        "updated_at": {
          "name": "updated_at",
          "type": "timestamp(3)",
          "primaryKey": false,
          "notNull": true,
          "default": "CURRENT_TIMESTAMP"
        },
        "integration_id": {
          "name": "integration_id",
          "type": "text",
          "primaryKey": false,
          "notNull": false
        },
        "pubFieldSchemaId": {
          "name": "pubFieldSchemaId",
          "type": "text",
          "primaryKey": false,
          "notNull": false
        },
        "slug": {
          "name": "slug",
          "type": "text",
          "primaryKey": false,
          "notNull": true
        }
      },
      "indexes": {
        "pub_fields_slug_key": {
          "name": "pub_fields_slug_key",
          "columns": [
            {
              "expression": "slug",
              "asc": true,
              "nulls": "last",
              "opclass": "text_ops",
              "isExpression": false
            }
          ],
          "isUnique": true,
          "concurrently": false,
          "method": "btree",
          "with": {}
        }
      },
      "foreignKeys": {
        "pub_fields_integration_id_fkey": {
          "name": "pub_fields_integration_id_fkey",
          "tableFrom": "pub_fields",
          "tableTo": "integrations",
          "schemaTo": "public",
          "columnsFrom": [
            "integration_id"
          ],
          "columnsTo": [
            "id"
          ],
          "onDelete": "set null",
          "onUpdate": "cascade"
        },
        "pub_fields_pubFieldSchemaId_fkey": {
          "name": "pub_fields_pubFieldSchemaId_fkey",
          "tableFrom": "pub_fields",
          "tableTo": "PubFieldSchema",
          "schemaTo": "public",
          "columnsFrom": [
            "pubFieldSchemaId"
          ],
          "columnsTo": [
            "id"
          ],
          "onDelete": "set null",
          "onUpdate": "cascade"
        }
      },
      "compositePrimaryKeys": {},
      "uniqueConstraints": {},
      "checkConstraints": {},
      "policies": {},
      "isRLSEnabled": false
    },
    "public._IntegrationInstanceToPub": {
      "name": "_IntegrationInstanceToPub",
      "schema": "",
      "columns": {
        "A": {
          "name": "A",
          "type": "text",
          "primaryKey": false,
          "notNull": true
        },
        "B": {
          "name": "B",
          "type": "text",
          "primaryKey": false,
          "notNull": true
        }
      },
      "indexes": {
        "_IntegrationInstanceToPub_AB_unique": {
          "name": "_IntegrationInstanceToPub_AB_unique",
          "columns": [
            {
              "expression": "A",
              "asc": true,
              "nulls": "last",
              "opclass": "text_ops",
              "isExpression": false
            },
            {
              "expression": "B",
              "asc": true,
              "nulls": "last",
              "opclass": "text_ops",
              "isExpression": false
            }
          ],
          "isUnique": true,
          "concurrently": false,
          "method": "btree",
          "with": {}
        },
        "_IntegrationInstanceToPub_B_index": {
          "name": "_IntegrationInstanceToPub_B_index",
          "columns": [
            {
              "expression": "B",
              "asc": true,
              "nulls": "last",
              "opclass": "text_ops",
              "isExpression": false
            }
          ],
          "isUnique": false,
          "concurrently": false,
          "method": "btree",
          "with": {}
        }
      },
      "foreignKeys": {
        "_IntegrationInstanceToPub_A_fkey": {
          "name": "_IntegrationInstanceToPub_A_fkey",
          "tableFrom": "_IntegrationInstanceToPub",
          "tableTo": "integration_instances",
          "schemaTo": "public",
          "columnsFrom": [
            "A"
          ],
          "columnsTo": [
            "id"
          ],
          "onDelete": "cascade",
          "onUpdate": "cascade"
        },
        "_IntegrationInstanceToPub_B_fkey": {
          "name": "_IntegrationInstanceToPub_B_fkey",
          "tableFrom": "_IntegrationInstanceToPub",
          "tableTo": "pubs",
          "schemaTo": "public",
          "columnsFrom": [
            "B"
          ],
          "columnsTo": [
            "id"
          ],
          "onDelete": "cascade",
          "onUpdate": "cascade"
        }
      },
      "compositePrimaryKeys": {},
      "uniqueConstraints": {},
      "checkConstraints": {},
      "policies": {},
      "isRLSEnabled": false
    },
    "public.integration_instances": {
      "name": "integration_instances",
      "schema": "",
      "columns": {
        "id": {
          "name": "id",
          "type": "text",
          "primaryKey": true,
          "notNull": true,
          "default": "gen_random_uuid()"
        },
        "name": {
          "name": "name",
          "type": "text",
          "primaryKey": false,
          "notNull": true
        },
        "integration_id": {
          "name": "integration_id",
          "type": "text",
          "primaryKey": false,
          "notNull": true
        },
        "created_at": {
          "name": "created_at",
          "type": "timestamp(3)",
          "primaryKey": false,
          "notNull": true,
          "default": "CURRENT_TIMESTAMP"
        },
        "updated_at": {
          "name": "updated_at",
          "type": "timestamp(3)",
          "primaryKey": false,
          "notNull": true,
          "default": "CURRENT_TIMESTAMP"
        },
        "community_id": {
          "name": "community_id",
          "type": "text",
          "primaryKey": false,
          "notNull": true
        },
        "stage_id": {
          "name": "stage_id",
          "type": "text",
          "primaryKey": false,
          "notNull": false
        },
        "config": {
          "name": "config",
          "type": "jsonb",
          "primaryKey": false,
          "notNull": false
        }
      },
      "indexes": {},
      "foreignKeys": {
        "integration_instances_integration_id_fkey": {
          "name": "integration_instances_integration_id_fkey",
          "tableFrom": "integration_instances",
          "tableTo": "integrations",
          "schemaTo": "public",
          "columnsFrom": [
            "integration_id"
          ],
          "columnsTo": [
            "id"
          ],
          "onDelete": "restrict",
          "onUpdate": "cascade"
        },
        "integration_instances_community_id_fkey": {
          "name": "integration_instances_community_id_fkey",
          "tableFrom": "integration_instances",
          "tableTo": "communities",
          "schemaTo": "public",
          "columnsFrom": [
            "community_id"
          ],
          "columnsTo": [
            "id"
          ],
          "onDelete": "restrict",
          "onUpdate": "cascade"
        },
        "integration_instances_stage_id_fkey": {
          "name": "integration_instances_stage_id_fkey",
          "tableFrom": "integration_instances",
          "tableTo": "stages",
          "schemaTo": "public",
          "columnsFrom": [
            "stage_id"
          ],
          "columnsTo": [
            "id"
          ],
          "onDelete": "set null",
          "onUpdate": "cascade"
        }
      },
      "compositePrimaryKeys": {},
      "uniqueConstraints": {},
      "checkConstraints": {},
      "policies": {},
      "isRLSEnabled": false
    },
    "public.action_instances": {
      "name": "action_instances",
      "schema": "",
      "columns": {
        "id": {
          "name": "id",
          "type": "text",
          "primaryKey": true,
          "notNull": true,
          "default": "gen_random_uuid()"
        },
        "stage_id": {
          "name": "stage_id",
          "type": "text",
          "primaryKey": false,
          "notNull": true
        },
        "created_at": {
          "name": "created_at",
          "type": "timestamp(3)",
          "primaryKey": false,
          "notNull": true,
          "default": "CURRENT_TIMESTAMP"
        },
        "updated_at": {
          "name": "updated_at",
          "type": "timestamp(3)",
          "primaryKey": false,
          "notNull": true,
          "default": "CURRENT_TIMESTAMP"
        },
        "config": {
          "name": "config",
          "type": "jsonb",
          "primaryKey": false,
          "notNull": false
        },
        "name": {
          "name": "name",
          "type": "text",
          "primaryKey": false,
          "notNull": true,
          "default": "''"
        },
        "action": {
          "name": "action",
          "type": "Action",
          "typeSchema": "public",
          "primaryKey": false,
          "notNull": true
        }
      },
      "indexes": {},
      "foreignKeys": {
        "action_instances_stage_id_fkey": {
          "name": "action_instances_stage_id_fkey",
          "tableFrom": "action_instances",
          "tableTo": "stages",
          "schemaTo": "public",
          "columnsFrom": [
            "stage_id"
          ],
          "columnsTo": [
            "id"
          ],
          "onDelete": "cascade",
          "onUpdate": "cascade"
        }
      },
      "compositePrimaryKeys": {},
      "uniqueConstraints": {},
      "checkConstraints": {},
      "policies": {},
      "isRLSEnabled": false
    },
    "public.permissions": {
      "name": "permissions",
      "schema": "",
      "columns": {
        "id": {
          "name": "id",
          "type": "text",
          "primaryKey": true,
          "notNull": true,
          "default": "gen_random_uuid()"
        },
        "member_id": {
          "name": "member_id",
          "type": "text",
          "primaryKey": false,
          "notNull": false
        },
        "member_group_id": {
          "name": "member_group_id",
          "type": "text",
          "primaryKey": false,
          "notNull": false
        },
        "created_at": {
          "name": "created_at",
          "type": "timestamp(3)",
          "primaryKey": false,
          "notNull": true,
          "default": "CURRENT_TIMESTAMP"
        },
        "updated_at": {
          "name": "updated_at",
          "type": "timestamp(3)",
          "primaryKey": false,
          "notNull": true,
          "default": "CURRENT_TIMESTAMP"
        }
      },
      "indexes": {},
      "foreignKeys": {
        "permissions_member_id_fkey": {
          "name": "permissions_member_id_fkey",
          "tableFrom": "permissions",
          "tableTo": "members",
          "schemaTo": "public",
          "columnsFrom": [
            "member_id"
          ],
          "columnsTo": [
            "id"
          ],
          "onDelete": "set null",
          "onUpdate": "cascade"
        },
        "permissions_member_group_id_fkey": {
          "name": "permissions_member_group_id_fkey",
          "tableFrom": "permissions",
          "tableTo": "member_groups",
          "schemaTo": "public",
          "columnsFrom": [
            "member_group_id"
          ],
          "columnsTo": [
            "id"
          ],
          "onDelete": "set null",
          "onUpdate": "cascade"
        }
      },
      "compositePrimaryKeys": {},
      "uniqueConstraints": {},
      "checkConstraints": {},
      "policies": {},
      "isRLSEnabled": false
    },
    "public._PermissionToPub": {
      "name": "_PermissionToPub",
      "schema": "",
      "columns": {
        "A": {
          "name": "A",
          "type": "text",
          "primaryKey": false,
          "notNull": true
        },
        "B": {
          "name": "B",
          "type": "text",
          "primaryKey": false,
          "notNull": true
        }
      },
      "indexes": {
        "_PermissionToPub_AB_unique": {
          "name": "_PermissionToPub_AB_unique",
          "columns": [
            {
              "expression": "A",
              "asc": true,
              "nulls": "last",
              "opclass": "text_ops",
              "isExpression": false
            },
            {
              "expression": "B",
              "asc": true,
              "nulls": "last",
              "opclass": "text_ops",
              "isExpression": false
            }
          ],
          "isUnique": true,
          "concurrently": false,
          "method": "btree",
          "with": {}
        },
        "_PermissionToPub_B_index": {
          "name": "_PermissionToPub_B_index",
          "columns": [
            {
              "expression": "B",
              "asc": true,
              "nulls": "last",
              "opclass": "text_ops",
              "isExpression": false
            }
          ],
          "isUnique": false,
          "concurrently": false,
          "method": "btree",
          "with": {}
        }
      },
      "foreignKeys": {
        "_PermissionToPub_A_fkey": {
          "name": "_PermissionToPub_A_fkey",
          "tableFrom": "_PermissionToPub",
          "tableTo": "permissions",
          "schemaTo": "public",
          "columnsFrom": [
            "A"
          ],
          "columnsTo": [
            "id"
          ],
          "onDelete": "cascade",
          "onUpdate": "cascade"
        },
        "_PermissionToPub_B_fkey": {
          "name": "_PermissionToPub_B_fkey",
          "tableFrom": "_PermissionToPub",
          "tableTo": "pubs",
          "schemaTo": "public",
          "columnsFrom": [
            "B"
          ],
          "columnsTo": [
            "id"
          ],
          "onDelete": "cascade",
          "onUpdate": "cascade"
        }
      },
      "compositePrimaryKeys": {},
      "uniqueConstraints": {},
      "checkConstraints": {},
      "policies": {},
      "isRLSEnabled": false
    },
    "public._PermissionToStage": {
      "name": "_PermissionToStage",
      "schema": "",
      "columns": {
        "A": {
          "name": "A",
          "type": "text",
          "primaryKey": false,
          "notNull": true
        },
        "B": {
          "name": "B",
          "type": "text",
          "primaryKey": false,
          "notNull": true
        }
      },
      "indexes": {
        "_PermissionToStage_AB_unique": {
          "name": "_PermissionToStage_AB_unique",
          "columns": [
            {
              "expression": "A",
              "asc": true,
              "nulls": "last",
              "opclass": "text_ops",
              "isExpression": false
            },
            {
              "expression": "B",
              "asc": true,
              "nulls": "last",
              "opclass": "text_ops",
              "isExpression": false
            }
          ],
          "isUnique": true,
          "concurrently": false,
          "method": "btree",
          "with": {}
        },
        "_PermissionToStage_B_index": {
          "name": "_PermissionToStage_B_index",
          "columns": [
            {
              "expression": "B",
              "asc": true,
              "nulls": "last",
              "opclass": "text_ops",
              "isExpression": false
            }
          ],
          "isUnique": false,
          "concurrently": false,
          "method": "btree",
          "with": {}
        }
      },
      "foreignKeys": {
        "_PermissionToStage_A_fkey": {
          "name": "_PermissionToStage_A_fkey",
          "tableFrom": "_PermissionToStage",
          "tableTo": "permissions",
          "schemaTo": "public",
          "columnsFrom": [
            "A"
          ],
          "columnsTo": [
            "id"
          ],
          "onDelete": "cascade",
          "onUpdate": "cascade"
        },
        "_PermissionToStage_B_fkey": {
          "name": "_PermissionToStage_B_fkey",
          "tableFrom": "_PermissionToStage",
          "tableTo": "stages",
          "schemaTo": "public",
          "columnsFrom": [
            "B"
          ],
          "columnsTo": [
            "id"
          ],
          "onDelete": "cascade",
          "onUpdate": "cascade"
        }
      },
      "compositePrimaryKeys": {},
      "uniqueConstraints": {},
      "checkConstraints": {},
      "policies": {},
      "isRLSEnabled": false
    },
    "public.rules": {
      "name": "rules",
      "schema": "",
      "columns": {
        "id": {
          "name": "id",
          "type": "text",
          "primaryKey": true,
          "notNull": true,
          "default": "gen_random_uuid()"
        },
        "event": {
          "name": "event",
          "type": "Event",
          "typeSchema": "public",
          "primaryKey": false,
          "notNull": true
        },
        "action_instance_id": {
          "name": "action_instance_id",
          "type": "text",
          "primaryKey": false,
          "notNull": true
        }
      },
      "indexes": {
        "rules_action_instance_id_event_key": {
          "name": "rules_action_instance_id_event_key",
          "columns": [
            {
              "expression": "action_instance_id",
              "asc": true,
              "nulls": "last",
              "opclass": "text_ops",
              "isExpression": false
            },
            {
              "expression": "event",
              "asc": true,
              "nulls": "last",
              "opclass": "text_ops",
              "isExpression": false
            }
          ],
          "isUnique": true,
          "concurrently": false,
          "method": "btree",
          "with": {}
        }
      },
      "foreignKeys": {
        "rules_action_instance_id_fkey": {
          "name": "rules_action_instance_id_fkey",
          "tableFrom": "rules",
          "tableTo": "action_instances",
          "schemaTo": "public",
          "columnsFrom": [
            "action_instance_id"
          ],
          "columnsTo": [
            "id"
          ],
          "onDelete": "cascade",
          "onUpdate": "cascade"
        }
      },
      "compositePrimaryKeys": {},
      "uniqueConstraints": {},
      "checkConstraints": {},
      "policies": {},
      "isRLSEnabled": false
    },
    "public._MemberGroupToUser": {
      "name": "_MemberGroupToUser",
      "schema": "",
      "columns": {
        "A": {
          "name": "A",
          "type": "text",
          "primaryKey": false,
          "notNull": true
        },
        "B": {
          "name": "B",
          "type": "text",
          "primaryKey": false,
          "notNull": true
        }
      },
      "indexes": {
        "_MemberGroupToUser_AB_unique": {
          "name": "_MemberGroupToUser_AB_unique",
          "columns": [
            {
              "expression": "A",
              "asc": true,
              "nulls": "last",
              "opclass": "text_ops",
              "isExpression": false
            },
            {
              "expression": "B",
              "asc": true,
              "nulls": "last",
              "opclass": "text_ops",
              "isExpression": false
            }
          ],
          "isUnique": true,
          "concurrently": false,
          "method": "btree",
          "with": {}
        },
        "_MemberGroupToUser_B_index": {
          "name": "_MemberGroupToUser_B_index",
          "columns": [
            {
              "expression": "B",
              "asc": true,
              "nulls": "last",
              "opclass": "text_ops",
              "isExpression": false
            }
          ],
          "isUnique": false,
          "concurrently": false,
          "method": "btree",
          "with": {}
        }
      },
      "foreignKeys": {
        "_MemberGroupToUser_A_fkey": {
          "name": "_MemberGroupToUser_A_fkey",
          "tableFrom": "_MemberGroupToUser",
          "tableTo": "member_groups",
          "schemaTo": "public",
          "columnsFrom": [
            "A"
          ],
          "columnsTo": [
            "id"
          ],
          "onDelete": "cascade",
          "onUpdate": "cascade"
        },
        "_MemberGroupToUser_B_fkey": {
          "name": "_MemberGroupToUser_B_fkey",
          "tableFrom": "_MemberGroupToUser",
          "tableTo": "users",
          "schemaTo": "public",
          "columnsFrom": [
            "B"
          ],
          "columnsTo": [
            "id"
          ],
          "onDelete": "cascade",
          "onUpdate": "cascade"
        }
      },
      "compositePrimaryKeys": {},
      "uniqueConstraints": {},
      "checkConstraints": {},
      "policies": {},
      "isRLSEnabled": false
    },
    "public.auth_tokens": {
      "name": "auth_tokens",
      "schema": "",
      "columns": {
        "id": {
          "name": "id",
          "type": "text",
          "primaryKey": true,
          "notNull": true
        },
        "hash": {
          "name": "hash",
          "type": "text",
          "primaryKey": false,
          "notNull": true
        },
        "created_at": {
          "name": "created_at",
          "type": "timestamp(3)",
          "primaryKey": false,
          "notNull": true,
          "default": "CURRENT_TIMESTAMP"
        },
        "expiresAt": {
          "name": "expiresAt",
          "type": "timestamp(3)",
          "primaryKey": false,
          "notNull": true
        },
        "isUsed": {
          "name": "isUsed",
          "type": "boolean",
          "primaryKey": false,
          "notNull": true,
          "default": false
        },
        "user_id": {
          "name": "user_id",
          "type": "text",
          "primaryKey": false,
          "notNull": true
        }
      },
      "indexes": {},
      "foreignKeys": {
        "auth_tokens_user_id_fkey": {
          "name": "auth_tokens_user_id_fkey",
          "tableFrom": "auth_tokens",
          "tableTo": "users",
          "schemaTo": "public",
          "columnsFrom": [
            "user_id"
          ],
          "columnsTo": [
            "id"
          ],
          "onDelete": "restrict",
          "onUpdate": "cascade"
        }
      },
      "compositePrimaryKeys": {},
      "uniqueConstraints": {},
      "checkConstraints": {},
      "policies": {},
      "isRLSEnabled": false
    },
    "public.PubFieldSchema": {
      "name": "PubFieldSchema",
      "schema": "",
      "columns": {
        "id": {
          "name": "id",
          "type": "text",
          "primaryKey": true,
          "notNull": true,
          "default": "gen_random_uuid()"
        },
        "namespace": {
          "name": "namespace",
          "type": "text",
          "primaryKey": false,
          "notNull": true
        },
        "name": {
          "name": "name",
          "type": "text",
          "primaryKey": false,
          "notNull": true
        },
        "schema": {
          "name": "schema",
          "type": "jsonb",
          "primaryKey": false,
          "notNull": true
        },
        "created_at": {
          "name": "created_at",
          "type": "timestamp(3)",
          "primaryKey": false,
          "notNull": true,
          "default": "CURRENT_TIMESTAMP"
        },
        "updated_at": {
          "name": "updated_at",
          "type": "timestamp(3)",
          "primaryKey": false,
          "notNull": true,
          "default": "CURRENT_TIMESTAMP"
        }
      },
      "indexes": {
        "PubFieldSchema_name_namespace_key": {
          "name": "PubFieldSchema_name_namespace_key",
          "columns": [
            {
              "expression": "name",
              "asc": true,
              "nulls": "last",
              "opclass": "text_ops",
              "isExpression": false
            },
            {
              "expression": "namespace",
              "asc": true,
              "nulls": "last",
              "opclass": "text_ops",
              "isExpression": false
            }
          ],
          "isUnique": true,
          "concurrently": false,
          "method": "btree",
          "with": {}
        }
      },
      "foreignKeys": {},
      "compositePrimaryKeys": {},
      "uniqueConstraints": {},
      "checkConstraints": {},
      "policies": {},
      "isRLSEnabled": false
    },
    "public.users": {
      "name": "users",
      "schema": "",
      "columns": {
        "id": {
          "name": "id",
          "type": "text",
          "primaryKey": true,
          "notNull": true,
          "default": "gen_random_uuid()"
        },
        "slug": {
          "name": "slug",
          "type": "text",
          "primaryKey": false,
          "notNull": true
        },
        "email": {
          "name": "email",
          "type": "text",
          "primaryKey": false,
          "notNull": true
        },
        "firstName": {
          "name": "firstName",
          "type": "text",
          "primaryKey": false,
          "notNull": true
        },
        "avatar": {
          "name": "avatar",
          "type": "text",
          "primaryKey": false,
          "notNull": false
        },
        "created_at": {
          "name": "created_at",
          "type": "timestamp(3)",
          "primaryKey": false,
          "notNull": true,
          "default": "CURRENT_TIMESTAMP"
        },
        "updated_at": {
          "name": "updated_at",
          "type": "timestamp(3)",
          "primaryKey": false,
          "notNull": true,
          "default": "CURRENT_TIMESTAMP"
        },
        "lastName": {
          "name": "lastName",
          "type": "text",
          "primaryKey": false,
          "notNull": false
        },
        "orcid": {
          "name": "orcid",
          "type": "text",
          "primaryKey": false,
          "notNull": false
        },
        "supabaseId": {
          "name": "supabaseId",
          "type": "text",
          "primaryKey": false,
          "notNull": false
        },
        "isSuperAdmin": {
          "name": "isSuperAdmin",
          "type": "boolean",
          "primaryKey": false,
          "notNull": true,
          "default": false
        }
      },
      "indexes": {
        "users_email_key": {
          "name": "users_email_key",
          "columns": [
            {
              "expression": "email",
              "asc": true,
              "nulls": "last",
              "opclass": "text_ops",
              "isExpression": false
            }
          ],
          "isUnique": true,
          "concurrently": false,
          "method": "btree",
          "with": {}
        },
        "users_slug_key": {
          "name": "users_slug_key",
          "columns": [
            {
              "expression": "slug",
              "asc": true,
              "nulls": "last",
              "opclass": "text_ops",
              "isExpression": false
            }
          ],
          "isUnique": true,
          "concurrently": false,
          "method": "btree",
          "with": {}
        },
        "users_supabaseId_key": {
          "name": "users_supabaseId_key",
          "columns": [
            {
              "expression": "supabaseId",
              "asc": true,
              "nulls": "last",
              "opclass": "text_ops",
              "isExpression": false
            }
          ],
          "isUnique": true,
          "concurrently": false,
          "method": "btree",
          "with": {}
        }
      },
      "foreignKeys": {},
      "compositePrimaryKeys": {},
      "uniqueConstraints": {},
      "checkConstraints": {},
      "policies": {},
      "isRLSEnabled": false
    },
    "public.integrations": {
      "name": "integrations",
      "schema": "",
      "columns": {
        "id": {
          "name": "id",
          "type": "text",
          "primaryKey": true,
          "notNull": true,
          "default": "gen_random_uuid()"
        },
        "created_at": {
          "name": "created_at",
          "type": "timestamp(3)",
          "primaryKey": false,
          "notNull": true,
          "default": "CURRENT_TIMESTAMP"
        },
        "updated_at": {
          "name": "updated_at",
          "type": "timestamp(3)",
          "primaryKey": false,
          "notNull": true,
          "default": "CURRENT_TIMESTAMP"
        },
        "actions": {
          "name": "actions",
          "type": "jsonb",
          "primaryKey": false,
          "notNull": true
        },
        "name": {
          "name": "name",
          "type": "text",
          "primaryKey": false,
          "notNull": true
        },
        "settingsUrl": {
          "name": "settingsUrl",
          "type": "text",
          "primaryKey": false,
          "notNull": true
        }
      },
      "indexes": {},
      "foreignKeys": {},
      "compositePrimaryKeys": {},
      "uniqueConstraints": {},
      "checkConstraints": {},
      "policies": {},
      "isRLSEnabled": false
    },
    "public.communities": {
      "name": "communities",
      "schema": "",
      "columns": {
        "id": {
          "name": "id",
          "type": "text",
          "primaryKey": true,
          "notNull": true,
          "default": "gen_random_uuid()"
        },
        "created_at": {
          "name": "created_at",
          "type": "timestamp(3)",
          "primaryKey": false,
          "notNull": true,
          "default": "CURRENT_TIMESTAMP"
        },
        "updated_at": {
          "name": "updated_at",
          "type": "timestamp(3)",
          "primaryKey": false,
          "notNull": true,
          "default": "CURRENT_TIMESTAMP"
        },
        "name": {
          "name": "name",
          "type": "text",
          "primaryKey": false,
          "notNull": true
        },
        "avatar": {
          "name": "avatar",
          "type": "text",
          "primaryKey": false,
          "notNull": false
        },
        "slug": {
          "name": "slug",
          "type": "text",
          "primaryKey": false,
          "notNull": true
        }
      },
      "indexes": {
        "communities_slug_key": {
          "name": "communities_slug_key",
          "columns": [
            {
              "expression": "slug",
              "asc": true,
              "nulls": "last",
              "opclass": "text_ops",
              "isExpression": false
            }
          ],
          "isUnique": true,
          "concurrently": false,
          "method": "btree",
          "with": {}
        }
      },
      "foreignKeys": {},
      "compositePrimaryKeys": {},
      "uniqueConstraints": {},
      "checkConstraints": {},
      "policies": {},
      "isRLSEnabled": false
    },
    "public.pubs": {
      "name": "pubs",
      "schema": "",
      "columns": {
        "id": {
          "name": "id",
          "type": "text",
          "primaryKey": true,
          "notNull": true,
          "default": "gen_random_uuid()"
        },
        "created_at": {
          "name": "created_at",
          "type": "timestamp(3)",
          "primaryKey": false,
          "notNull": true,
          "default": "CURRENT_TIMESTAMP"
        },
        "updated_at": {
          "name": "updated_at",
          "type": "timestamp(3)",
          "primaryKey": false,
          "notNull": true,
          "default": "CURRENT_TIMESTAMP"
        },
        "pub_type_id": {
          "name": "pub_type_id",
          "type": "text",
          "primaryKey": false,
          "notNull": true
        },
        "community_id": {
          "name": "community_id",
          "type": "text",
          "primaryKey": false,
          "notNull": true
        },
        "valuesBlob": {
          "name": "valuesBlob",
          "type": "jsonb",
          "primaryKey": false,
          "notNull": false
        },
        "parent_id": {
          "name": "parent_id",
          "type": "text",
          "primaryKey": false,
          "notNull": false
        },
        "assignee_id": {
          "name": "assignee_id",
          "type": "text",
          "primaryKey": false,
          "notNull": false
        }
      },
      "indexes": {},
      "foreignKeys": {
        "pubs_pub_type_id_fkey": {
          "name": "pubs_pub_type_id_fkey",
          "tableFrom": "pubs",
          "tableTo": "pub_types",
          "schemaTo": "public",
          "columnsFrom": [
            "pub_type_id"
          ],
          "columnsTo": [
            "id"
          ],
          "onDelete": "restrict",
          "onUpdate": "cascade"
        },
        "pubs_parent_id_fkey": {
          "name": "pubs_parent_id_fkey",
          "tableFrom": "pubs",
          "tableTo": "pubs",
          "schemaTo": "public",
          "columnsFrom": [
            "parent_id"
          ],
          "columnsTo": [
            "id"
          ],
          "onDelete": "cascade",
          "onUpdate": "cascade"
        },
        "pubs_community_id_fkey": {
          "name": "pubs_community_id_fkey",
          "tableFrom": "pubs",
          "tableTo": "communities",
          "schemaTo": "public",
          "columnsFrom": [
            "community_id"
          ],
          "columnsTo": [
            "id"
          ],
          "onDelete": "restrict",
          "onUpdate": "cascade"
        },
        "pubs_assignee_id_fkey": {
          "name": "pubs_assignee_id_fkey",
          "tableFrom": "pubs",
          "tableTo": "users",
          "schemaTo": "public",
          "columnsFrom": [
            "assignee_id"
          ],
          "columnsTo": [
            "id"
          ],
          "onDelete": "set null",
          "onUpdate": "cascade"
        }
      },
      "compositePrimaryKeys": {},
      "uniqueConstraints": {},
      "checkConstraints": {},
      "policies": {},
      "isRLSEnabled": false
    },
    "public.members": {
      "name": "members",
      "schema": "",
      "columns": {
        "id": {
          "name": "id",
          "type": "text",
          "primaryKey": true,
          "notNull": true,
          "default": "gen_random_uuid()"
        },
        "created_at": {
          "name": "created_at",
          "type": "timestamp(3)",
          "primaryKey": false,
          "notNull": true,
          "default": "CURRENT_TIMESTAMP"
        },
        "updated_at": {
          "name": "updated_at",
          "type": "timestamp(3)",
          "primaryKey": false,
          "notNull": true,
          "default": "CURRENT_TIMESTAMP"
        },
        "canAdmin": {
          "name": "canAdmin",
          "type": "boolean",
          "primaryKey": false,
          "notNull": true
        },
        "community_id": {
          "name": "community_id",
          "type": "text",
          "primaryKey": false,
          "notNull": true
        },
        "user_id": {
          "name": "user_id",
          "type": "text",
          "primaryKey": false,
          "notNull": true
        }
      },
      "indexes": {},
      "foreignKeys": {
        "members_community_id_fkey": {
          "name": "members_community_id_fkey",
          "tableFrom": "members",
          "tableTo": "communities",
          "schemaTo": "public",
          "columnsFrom": [
            "community_id"
          ],
          "columnsTo": [
            "id"
          ],
          "onDelete": "cascade",
          "onUpdate": "cascade"
        },
        "members_user_id_fkey": {
          "name": "members_user_id_fkey",
          "tableFrom": "members",
          "tableTo": "users",
          "schemaTo": "public",
          "columnsFrom": [
            "user_id"
          ],
          "columnsTo": [
            "id"
          ],
          "onDelete": "restrict",
          "onUpdate": "cascade"
        }
      },
      "compositePrimaryKeys": {},
      "uniqueConstraints": {},
      "checkConstraints": {},
      "policies": {},
      "isRLSEnabled": false
    },
    "public.member_groups": {
      "name": "member_groups",
      "schema": "",
      "columns": {
        "id": {
          "name": "id",
          "type": "text",
          "primaryKey": true,
          "notNull": true,
          "default": "gen_random_uuid()"
        },
        "created_at": {
          "name": "created_at",
          "type": "timestamp(3)",
          "primaryKey": false,
          "notNull": true,
          "default": "CURRENT_TIMESTAMP"
        },
        "updated_at": {
          "name": "updated_at",
          "type": "timestamp(3)",
          "primaryKey": false,
          "notNull": true,
          "default": "CURRENT_TIMESTAMP"
        },
        "canAdmin": {
          "name": "canAdmin",
          "type": "boolean",
          "primaryKey": false,
          "notNull": true
        },
        "community_id": {
          "name": "community_id",
          "type": "text",
          "primaryKey": false,
          "notNull": true
        }
      },
      "indexes": {},
      "foreignKeys": {
        "member_groups_community_id_fkey": {
          "name": "member_groups_community_id_fkey",
          "tableFrom": "member_groups",
          "tableTo": "communities",
          "schemaTo": "public",
          "columnsFrom": [
            "community_id"
          ],
          "columnsTo": [
            "id"
          ],
          "onDelete": "restrict",
          "onUpdate": "cascade"
        }
      },
      "compositePrimaryKeys": {},
      "uniqueConstraints": {},
      "checkConstraints": {},
      "policies": {},
      "isRLSEnabled": false
    },
    "public.stages": {
      "name": "stages",
      "schema": "",
      "columns": {
        "id": {
          "name": "id",
          "type": "text",
          "primaryKey": true,
          "notNull": true,
          "default": "gen_random_uuid()"
        },
        "created_at": {
          "name": "created_at",
          "type": "timestamp(3)",
          "primaryKey": false,
          "notNull": true,
          "default": "CURRENT_TIMESTAMP"
        },
        "updated_at": {
          "name": "updated_at",
          "type": "timestamp(3)",
          "primaryKey": false,
          "notNull": true,
          "default": "CURRENT_TIMESTAMP"
        },
        "name": {
          "name": "name",
          "type": "text",
          "primaryKey": false,
          "notNull": true
        },
        "order": {
          "name": "order",
          "type": "text",
          "primaryKey": false,
          "notNull": true
        },
        "community_id": {
          "name": "community_id",
          "type": "text",
          "primaryKey": false,
          "notNull": true
        }
      },
      "indexes": {},
      "foreignKeys": {
        "stages_community_id_fkey": {
          "name": "stages_community_id_fkey",
          "tableFrom": "stages",
          "tableTo": "communities",
          "schemaTo": "public",
          "columnsFrom": [
            "community_id"
          ],
          "columnsTo": [
            "id"
          ],
          "onDelete": "restrict",
          "onUpdate": "cascade"
        }
      },
      "compositePrimaryKeys": {},
      "uniqueConstraints": {},
      "checkConstraints": {},
      "policies": {},
      "isRLSEnabled": false
    },
    "public.PubsInStages": {
      "name": "PubsInStages",
      "schema": "",
      "columns": {
        "pubId": {
          "name": "pubId",
          "type": "text",
          "primaryKey": false,
          "notNull": true
        },
        "stageId": {
          "name": "stageId",
          "type": "text",
          "primaryKey": false,
          "notNull": true
        }
      },
      "indexes": {},
      "foreignKeys": {
        "PubsInStages_pubId_fkey": {
          "name": "PubsInStages_pubId_fkey",
          "tableFrom": "PubsInStages",
          "tableTo": "pubs",
          "schemaTo": "public",
          "columnsFrom": [
            "pubId"
          ],
          "columnsTo": [
            "id"
          ],
          "onDelete": "cascade",
          "onUpdate": "cascade"
        },
        "PubsInStages_stageId_fkey": {
          "name": "PubsInStages_stageId_fkey",
          "tableFrom": "PubsInStages",
          "tableTo": "stages",
          "schemaTo": "public",
          "columnsFrom": [
            "stageId"
          ],
          "columnsTo": [
            "id"
          ],
          "onDelete": "cascade",
          "onUpdate": "cascade"
        }
      },
      "compositePrimaryKeys": {
        "PubsInStages_pkey": {
          "name": "PubsInStages_pkey",
          "columns": [
            "pubId",
            "stageId"
          ]
        }
      },
      "uniqueConstraints": {},
      "checkConstraints": {},
      "policies": {},
      "isRLSEnabled": false
    },
    "public.move_constraint": {
      "name": "move_constraint",
      "schema": "",
      "columns": {
        "stage_id": {
          "name": "stage_id",
          "type": "text",
          "primaryKey": false,
          "notNull": true
        },
        "destination_id": {
          "name": "destination_id",
          "type": "text",
          "primaryKey": false,
          "notNull": true
        },
        "created_at": {
          "name": "created_at",
          "type": "timestamp(3)",
          "primaryKey": false,
          "notNull": true,
          "default": "CURRENT_TIMESTAMP"
        },
        "updated_at": {
          "name": "updated_at",
          "type": "timestamp(3)",
          "primaryKey": false,
          "notNull": true,
          "default": "CURRENT_TIMESTAMP"
        }
      },
      "indexes": {},
      "foreignKeys": {
        "move_constraint_stage_id_fkey": {
          "name": "move_constraint_stage_id_fkey",
          "tableFrom": "move_constraint",
          "tableTo": "stages",
          "schemaTo": "public",
          "columnsFrom": [
            "stage_id"
          ],
          "columnsTo": [
            "id"
          ],
          "onDelete": "cascade",
          "onUpdate": "cascade"
        },
        "move_constraint_destination_id_fkey": {
          "name": "move_constraint_destination_id_fkey",
          "tableFrom": "move_constraint",
          "tableTo": "stages",
          "schemaTo": "public",
          "columnsFrom": [
            "destination_id"
          ],
          "columnsTo": [
            "id"
          ],
          "onDelete": "cascade",
          "onUpdate": "cascade"
        }
      },
      "compositePrimaryKeys": {
        "move_constraint_pkey": {
          "name": "move_constraint_pkey",
          "columns": [
            "stage_id",
            "destination_id"
          ]
        }
      },
      "uniqueConstraints": {},
      "checkConstraints": {},
      "policies": {},
      "isRLSEnabled": false
    }
  },
  "enums": {
    "public.Action": {
      "name": "Action",
      "values": [
        "log",
        "pdf",
        "email",
        "pushToV6"
      ],
      "schema": "public"
    },
    "public.Event": {
      "name": "Event",
      "values": [
        "pubEnteredStage",
        "pubLeftStage"
      ],
      "schema": "public"
    }
  },
  "schemas": {},
  "sequences": {},
  "roles": {},
  "policies": {},
  "views": {},
  "_meta": {
    "schemas": {},
    "tables": {},
    "columns": {}
  },
  "internal": {
    "tables": {}
  }
}